cgsense2023/__init__.py
cgsense2023/_modidx.py
cgsense2023/io.py
cgsense2023/math.py
cgsense2023/metrics.py
cgsense2023/mri.py
cgsense2023/optimizer.py
cgsense2023/plot.py
cgsense2023/utils.py
cgsense2023-0.0.6.dist-info/LICENSE
cgsense2023-0.0.6.dist-info/METADATA
cgsense2023-0.0.6.dist-info/WHEEL
cgsense2023-0.0.6.dist-info/entry_points.txt
cgsense2023-0.0.6.dist-info/top_level.txt
cgsense2023-0.0.6.dist-info/RECORD
