Metadata-Version: 2.1
Name: cgsense2023
Version: 0.0.6
Summary: Conjugate Gradient SENSE (CG-SENSE) MRI Reconstruction
Home-page: https://github.com/hdocmsu/cgsense2023/
Author: Hung Do, PhD
Author-email: clinicalcollaborations@gmail.com
License: MIT License
Keywords: nbdev
Classifier: Development Status :: 3 - Alpha
Classifier: Intended Audience :: Developers
Classifier: Natural Language :: English
Classifier: Programming Language :: Python :: 3.7
Classifier: Programming Language :: Python :: 3.8
Classifier: Programming Language :: Python :: 3.9
Classifier: Programming Language :: Python :: 3.10
Classifier: License :: OSI Approved :: MIT License
Requires-Python: >=3.7
License-File: LICENSE
Requires-Dist: jupyter-compare-view
Requires-Dist: scikit-image
Requires-Dist: matplotlib
Requires-Dist: seaborn
Requires-Dist: prettytable
Requires-Dist: h5py
Requires-Dist: scipy
Requires-Dist: pyfftw
Provides-Extra: dev
